setup.py
dictvalidator/__init__.py
dictvalidator/core.py
dictvalidator/exceptions.py
dictvalidator/fields.py
dictvalidator/meta.py
dictvalidator/validators.py
dictvalidator.egg-info/PKG-INFO
dictvalidator.egg-info/SOURCES.txt
dictvalidator.egg-info/dependency_links.txt
dictvalidator.egg-info/namespace_packages.txt
dictvalidator.egg-info/not-zip-safe
dictvalidator.egg-info/top_level.txt