Metadata-Version: 1.1
Name: dictvalidator
Version: 0.1.2
Summary: Python module for validating dictionaries against a schema
Home-page: http://github.com/greenwoodcm/dict-validator
Author: Chris Greenwood
Author-email: greenwoodcm@gmail.com
License: BSD
Platform: any
Classifier: Development Status :: 4 - Beta
Classifier: Environment :: Web Environment
Classifier: Intended Audience :: Developers
Classifier: License :: OSI Approved :: BSD License
Classifier: Operating System :: OS Independent
Classifier: Programming Language :: Python
Classifier: Topic :: Internet :: WWW/HTTP :: Dynamic Content
Classifier: Topic :: Software Development :: Libraries :: Python Modules
